{"version": 0.6, "generator": "Overpass API 0.7.59 e21c39fe", "osm3s": {"timestamp_osm_base": "2023-03-01T08:37:51Z", "copyright": "The data included in this document is from www.openstreetmap.org. The data is made available under ODbL."}, "elements": [{"type": "node", "id": 3446962254, "lat": 47.1907898, "lon": 19.0069788, "tags": {"artist_name": "Marjay Gy\u00f6rgy", "artwork_type": "bust", "name": "Pet\u0151fi S\u00e1ndor", "tourism": "artwork"}}, {"type": "node", "id": 3454477874, "lat": 46.968367, "lon": 18.942133, "tags": {"alt_name": "Ac\u00e9lcs\u0151templom", "art_type": "sculpture", "artist_name": "Szanyi P\u00e9ter", "artwork_type": "sculpture", "material": "steel", "name": "Mement\u00f3", "source": "http://steelsculpture.art/hu/szoborpark/", "source:date": "2021-11-14", "start_date": "1996", "tourism": "artwork", "url": "http://turistautak.hu/poi.php?id=67025"}}, {"type": "node", "id": 3454477885, "lat": 46.9642839, "lon": 18.9455034, "tags": {"artwork_type": "statue", "name": "Arat\u00f3k", "source": "turistautak.hu", "source:date": "2015-01-12", "tourism": "artwork", "url": "http://turistautak.hu/poi.php?id=98069"}}, {"type": "node", "id": 3454478445, "lat": 46.959093, "lon": 18.945024, "tags": {"artist_name": "Somogyi J\u00f3zsef", "artwork_type": "statue", "name": "Martin\u00e1sz-szobor", "source:date": "2012-01-01", "tourism": "artwork", "url": "http://turistautak.hu/poi.php?id=78789", "website": "https://www.kozterkep.hu/3020/martinasz"}}, {"type": "node", "id": 3454478655, "lat": 46.966665, "lon": 18.948366, "tags": {"alt_name": "1/2 x = V (Felix = Vikt\u00f3ria", "artist_name": "Gal\u00e1ntai Gy\u00f6rgy", "artwork_type": "sculpture", "material": "steel plate", "name": "Zsir\u00e1fok", "source": "turistautak.hu", "source:date": "2015-01-12", "start_date": "1979", "tourism": "artwork", "url": "http://turistautak.hu/poi.php?id=98068"}}, {"type": "node", "id": 3459827156, "lat": 47.118492, "lon": 18.575592, "tags": {"artwork_type": "statue", "source": "turistautak.hu", "source:date": "2015-01-12", "tourism": "artwork", "url": "http://turistautak.hu/poi.php?id=29182"}}, {"type": "node", "id": 3461941847, "lat": 47.022847, "lon": 19.098613, "tags": {"artwork_type": "statue", "name": "Kunbaba", "source": "turistautak.hu", "source:date": "2014-08-10", "tourism": "artwork", "url": "http://turistautak.hu/poi.php?id=142461"}}, {"type": "node", "id": 3461942208, "lat": 47.026777, "lon": 19.122625, "tags": {"artwork_type": "statue", "name": "Sz\u00e1mad\u00f3 juh\u00e1sz", "source": "turistautak.hu", "source:date": "2012-10-15", "tourism": "artwork", "url": "http://turistautak.hu/poi.php?id=123155"}}, {"type": "node", "id": 3461942226, "lat": 47.027217, "lon": 19.122683, "tags": {"artwork_type": "statue", "name": "Vir\u00e1gh Gedeon mellszobra", "source": "turistautak.hu", "source:date": "2013-05-27", "tourism": "artwork", "url": "http://turistautak.hu/poi.php?id=154004"}}, {"type": "node", "id": 3465808474, "lat": 47.3516018, "lon": 19.0990623, "tags": {"artwork_type": "statue", "name": "Pet\u0151fi S\u00e1ndor", "source": "turistautak.hu", "source:date": "2013-03-20", "tourism": "artwork", "url": "http://turistautak.hu/poi.php?id=151697"}}, {"type": "node", "id": 3465808600, "lat": 47.355039, "lon": 19.087993, "tags": {"artwork_type": "statue", "name": "Turul", "source": "turistautak.hu", "source:date": "2012-11-19", "tourism": "artwork", "url": "http://turistautak.hu/poi.php?id=147092"}}, {"type": "node", "id": 3488385367, "lat": 47.2011074, "lon": 19.0107853, "tags": {"artwork_type": "statue", "name": "Kunbaba", "source": "survey", "source:date": "2011-08-09", "tourism": "artwork"}}, {"type": "node", "id": 3488447746, "lat": 47.319867, "lon": 18.911717, "tags": {"artwork_type": "statue", "description": "Anya gyermek\u00e9vel.", "source": "turistautak.hu", "source:date": "2014-06-07", "tourism": "artwork", "url": "http://turistautak.hu/poi.php?id=169101"}}, {"type": "node", "id": 3488447748, "lat": 47.3218, "lon": 18.9102, "tags": {"artwork_type": "statue", "source": "turistautak.hu", "source:date": "2014-06-07", "tourism": "artwork", "url": "http://turistautak.hu/poi.php?id=169102"}}, {"type": "node", "id": 3644647501, "lat": 47.2475739, "lon": 18.8989615, "tags": {"artwork_type": "sculpture", "name": "Ercsi c\u00edmere", "tourism": "artwork"}}, {"type": "node", "id": 3644647510, "lat": 47.2470277, "lon": 18.9037461, "tags": {"artwork_type": "sculpture", "name": "T\u00f6r\u00f6k basa", "tourism": "artwork"}}, {"type": "node", "id": 3654506406, "lat": 47.3216484, "lon": 18.9613022, "tags": {"artwork_type": "sculpture", "name": "C\u00edmeres Orsz\u00e1galma", "tourism": "artwork"}}, {"type": "node", "id": 3659906430, "lat": 47.2668903, "lon": 18.834487, "tags": {"artwork_type": "M\u00e1ria-szobor", "tourism": "artwork"}}, {"type": "node", "id": 3661432729, "lat": 47.196386, "lon": 18.6065784, "tags": {"artwork_type": "statue", "name": "Csodaszarvas", "tourism": "artwork"}}, {"type": "node", "id": 3661432731, "lat": 47.1895083, "lon": 18.623691, "tags": {"artwork_type": "statue", "name": "F\u00e9s\u00fclk\u00f6d\u0151 n\u0151i akt", "tourism": "artwork"}}, {"type": "node", "id": 3661432732, "lat": 47.1950404, "lon": 18.6051289, "tags": {"artwork_type": "statue", "name": "J\u00e9zus szobor", "tourism": "artwork"}}, {"type": "node", "id": 3661432733, "lat": 47.1968314, "lon": 18.6073552, "tags": {"artwork_type": "statue", "name": "Kozmikus forma", "tourism": "artwork"}}, {"type": "node", "id": 3661432735, "lat": 47.1969784, "lon": 18.6080265, "tags": {"artwork_type": "statue", "name": "T\u00f3 t\u00fcnd\u00e9re", "tourism": "artwork"}}, {"type": "node", "id": 3661432736, "lat": 47.1968256, "lon": 18.6076149, "tags": {"artwork_type": "statue", "name": "V\u00edzbe l\u00e9p\u0151 l\u00e1ny", "tourism": "artwork"}}, {"type": "node", "id": 3661552249, "lat": 47.2078709, "lon": 18.6288253, "tags": {"artwork_type": "sculpture", "name": "F\u00fcrd\u0151z\u0151 gyerekek domborm\u0171ve", "tourism": "artwork"}}, {"type": "node", "id": 3661552253, "lat": 47.2055484, "lon": 18.6284764, "tags": {"artwork_type": "statue", "name": "Szocialista m\u0171v\u00e9szet", "tourism": "artwork", "website": "https://www.kozterkep.hu/5283/"}}, {"type": "node", "id": 3661694163, "lat": 47.1266789, "lon": 18.6686723, "tags": {"artwork_type": "statue", "name": "Kos-szobor", "tourism": "artwork"}}, {"type": "node", "id": 3662672556, "lat": 47.2896879, "lon": 18.6518905, "tags": {"artwork_type": "statue", "name": "Szenth\u00e1roms\u00e1g szobor", "tourism": "artwork"}}, {"type": "node", "id": 3662792825, "lat": 47.2451021, "lon": 18.6268885, "tags": {"artwork_type": "statue", "name": "V\u00e9n bor\u00e1sz szobor", "tourism": "artwork"}}, {"type": "node", "id": 3978112509, "lat": 47.1506396, "lon": 18.8267719, "tags": {"artwork_type": "statue", "name": "Herkules harca a lernai H\u00fcdr\u00e1val", "tourism": "artwork"}}, {"type": "node", "id": 4409515192, "lat": 47.3501735, "lon": 18.6896022, "tags": {"alt_name": "Szent Mih\u00e1ly szobor", "artist_name": "Szpisj\u00e1k P\u00e1l", "artwork_type": "statue", "name": "Saint Michael", "tourism": "artwork"}}, {"type": "node", "id": 4608562320, "lat": 47.3250759, "lon": 18.9973723, "tags": {"artwork_type": "stone", "name": "Eur\u00f3pai m\u00e9rf\u00f6ldk\u0151", "tourism": "artwork"}}, {"type": "node", "id": 4728723526, "lat": 47.3031657, "lon": 18.8055183, "tags": {"artwork_type": "statue", "material": "stone", "name": "Szenth\u00e1roms\u00e1g", "tourism": "artwork"}}, {"type": "node", "id": 4826749476, "lat": 46.9604832, "lon": 18.939462, "tags": {"artwork_type": "statue", "name": "Vir\u00e1g\u00e1gy egy medence hely\u00e9n", "source": "http://zoldkalauz.hu/dunaujvaros-petofi-muveszeti-liget", "tourism": "artwork"}}, {"type": "node", "id": 4826749478, "lat": 46.958592, "lon": 18.9407316, "tags": {"artist_name": "Somogyi J\u00f3zsef", "artwork_type": "fountain", "name": "\u00d6ntelt Mack\u00f3", "tourism": "artwork"}}, {"type": "node", "id": 4826749480, "lat": 46.9583766, "lon": 18.9382326, "tags": {"tourism": "artwork"}}, {"type": "node", "id": 4866586141, "lat": 47.3174999, "lon": 18.9087132, "tags": {"name": "#helloBATTA", "tourism": "artwork"}}, {"type": "node", "id": 5276413227, "lat": 47.1256691, "lon": 18.828555, "tags": {"tourism": "artwork"}}, {"type": "node", "id": 5849887685, "lat": 47.2781744, "lon": 19.0697646, "tags": {"name": "XXIII. J\u00e1nos p\u00e1pa", "tourism": "artwork"}}, {"type": "node", "id": 5849913187, "lat": 47.2764889, "lon": 19.065664, "tags": {"artist_name": "Szab\u00f3 Zolt\u00e1n", "artwork_type": "statue", "name": "Gr\u00f3f Sz\u00e9chenyi Istv\u00e1n", "tourism": "artwork"}}, {"type": "node", "id": 5849913188, "lat": 47.2764472, "lon": 19.0657173, "tags": {"artist_name": "Szab\u00f3 Zolt\u00e1n", "artwork_type": "statue", "name": "De\u00e1k Ferenc", "tourism": "artwork"}}, {"type": "node", "id": 6580452117, "lat": 47.2912404, "lon": 18.8141389, "tags": {"artwork_type": "statue", "material": "brass", "name": "Auguszta 26 t\u00f6rt\u00e9nete", "tourism": "artwork"}}, {"type": "node", "id": 7638133062, "lat": 47.180642, "lon": 19.0024157, "tags": {"artwork_type": "statue", "name": "IV. (Kun) L\u00e1szl\u00f3 kir\u00e1ly", "tourism": "artwork"}}, {"type": "node", "id": 8254885945, "lat": 47.2844652, "lon": 18.6538543, "tags": {"artwork_type": "statue", "material": "wood", "name": "Onesty\u00e1k L\u00e1szl\u00f3", "tourism": "artwork"}}, {"type": "node", "id": 9043642466, "lat": 47.1685795, "lon": 18.944251, "tags": {"artwork_type": "statue", "tourism": "artwork"}}, {"type": "node", "id": 9167632295, "lat": 47.3459904, "lon": 19.0441079, "tags": {"addr:street": "Gyergy\u00f3szentmikl\u00f3s t\u00e9r", "artist_name": "Szab\u00f3 Zolt\u00e1n", "description": "a m\u0171v\u00e9sz rov\u00e1s farag\u00e1ssal \u00edrta r\u00e1 a nev\u00e9t", "image": "http://www.rovasirasforrai.hu/Fenykeptar/1_Kep/076b_Faragott-kopjafa_Szigetszentmiklos_Varga-Gabor_IMGP0153.jpg;http://www.rovasirasforrai.hu/Fenykeptar/1_Kep/076a_Faragott-kopjafa_Szigetszentmiklos_Varga-Gabor_IMGP0155.jpg", "inscription": "\ud803\udc8c\ud803\udc80\ud803\udca2\ud803\udc80\ud803\udc8d\ud803\udca6\ud803\udc80 \ud803\udca5\ud803\udc80\ud803\udc82\ud803\udc9c \ud803\udcaf\ud803\udc9b\ud803\udc96\ud803\udca6\ud803\udc81\ud803\udc99", "name": "aragott kopjafa a 15. SZER tal\u00e1lkoz\u00f3 eml\u00e9k\u00e9re, 2003.", "start_date": "2003", "tourism": "artwork"}}, {"type": "node", "id": 9169760236, "lat": 47.1806796, "lon": 18.9411896, "tags": {"artist_name": "Nemes Ferenc fafarag\u00f3", "description": "faragott fa oszlop rov\u00e1s felirattal, amely alulr\u00f3l f\u00f6lfel\u00e9 olvasand\u00f3", "direction": "355", "inscription": "\ud803\udca2\ud803\udc81\ud803\udc84\ud803\udc93\ud803\udc89\ud803\udcae\ud803\udc89", "name": "telep\u00fcl\u00e9sn\u00e9v oszlop", "tourism": "artwork"}}, {"type": "node", "id": 9169760237, "lat": 47.1655041, "lon": 18.9529671, "tags": {"artist_name": "Nemes Ferenc fafarag\u00f3", "description": "faragott fa oszlop rov\u00e1s felirattal, amely alulr\u00f3l f\u00f6lfel\u00e9 olvasand\u00f3", "direction": "40", "inscription": "\ud803\udca2\ud803\udc81\ud803\udc84\ud803\udc93\ud803\udc89\ud803\udcae\ud803\udc89", "name": "telep\u00fcl\u00e9sn\u00e9v oszlop", "tourism": "artwork"}}, {"type": "node", "id": 9249965381, "lat": 46.9633226, "lon": 18.948695}, {"type": "node", "id": 9249965382, "lat": 46.9634249, "lon": 18.9487299}, {"type": "node", "id": 9249965383, "lat": 46.9634366, "lon": 18.9486561}, {"type": "node", "id": 9249965384, "lat": 46.9633343, "lon": 18.9486212}, {"type": "node", "id": 9249965385, "lat": 46.9624782, "lon": 18.949527}, {"type": "node", "id": 9249965386, "lat": 46.9624627, "lon": 18.9496142}, {"type": "node", "id": 9249965387, "lat": 46.9624153, "lon": 18.9495962}, {"type": "node", "id": 9249965388, "lat": 46.9624308, "lon": 18.9495089}, {"type": "node", "id": 9249965389, "lat": 46.9619725, "lon": 18.9495904}, {"type": "node", "id": 9249965390, "lat": 46.9619835, "lon": 18.9496564}, {"type": "node", "id": 9249965391, "lat": 46.9618484, "lon": 18.9497047}, {"type": "node", "id": 9249965392, "lat": 46.9618374, "lon": 18.9496387}, {"type": "node", "id": 9249965393, "lat": 46.9612733, "lon": 18.9504806}, {"type": "node", "id": 9249965394, "lat": 46.961278, "lon": 18.9505298}, {"type": "node", "id": 9249965395, "lat": 46.9612025, "lon": 18.9505454}, {"type": "node", "id": 9249965396, "lat": 46.9611978, "lon": 18.9504962}, {"type": "node", "id": 9249965397, "lat": 46.9649579, "lon": 18.9475322, "tags": {"artist_name": "Bohus Zolt\u00e1n", "artwork_type": "sculpture", "material": "steel", "name": "Hengerek", "source": "http://steelsculpture.art/hu/szoborpark/", "start_date": "1975", "tourism": "artwork"}}, {"type": "node", "id": 9268735929, "lat": 47.3495653, "lon": 19.0434275, "tags": {"memorial": "statue", "tourism": "artwork"}}, {"type": "node", "id": 9611019969, "lat": 47.0376643, "lon": 18.9810987, "tags": {"artwork_type": "sculpture", "tourism": "artwork"}}, {"type": "node", "id": 9697910565, "lat": 46.9609078, "lon": 18.9344953, "tags": {"artist_name": "Fridrich Ferenc", "artwork_type": "statue", "name": "horizont\u00e1lis nap\u00f3ra", "tourism": "artwork"}}, {"type": "node", "id": 9698465545, "lat": 46.960899, "lon": 18.934433}, {"type": "node", "id": 9698465546, "lat": 46.960908, "lon": 18.9344358}, {"type": "node", "id": 9698465547, "lat": 46.960917, "lon": 18.9344405}, {"type": "node", "id": 9698465548, "lat": 46.9609241, "lon": 18.9344471}, {"type": "node", "id": 9698465549, "lat": 46.9609311, "lon": 18.9344565}, {"type": "node", "id": 9698465550, "lat": 46.9609353, "lon": 18.9344664}, {"type": "node", "id": 9698465551, "lat": 46.9609392, "lon": 18.9344806}, {"type": "node", "id": 9698465552, "lat": 46.9609401, "lon": 18.9344924}, {"type": "node", "id": 9698465553, "lat": 46.9609401, "lon": 18.9345023}, {"type": "node", "id": 9698465554, "lat": 46.9609393, "lon": 18.9345128}, {"type": "node", "id": 9698465555, "lat": 46.9609369, "lon": 18.9345238}, {"type": "node", "id": 9698465556, "lat": 46.9609317, "lon": 18.9345347}, {"type": "node", "id": 9698465557, "lat": 46.9609248, "lon": 18.9345451}, {"type": "node", "id": 9698465558, "lat": 46.9609167, "lon": 18.9345519}, {"type": "node", "id": 9698465559, "lat": 46.9609086, "lon": 18.9345541}, {"type": "node", "id": 9698465560, "lat": 46.9609015, "lon": 18.9345537}, {"type": "node", "id": 9698465561, "lat": 46.9608948, "lon": 18.9345499}, {"type": "node", "id": 9741257418, "lat": 47.1971684, "lon": 18.6083956, "tags": {"artwork_subject": "Hatty\u00fak \u00e9s t\u0151k\u00e9s r\u00e9c\u00e9k", "artwork_type": "statue", "material": "metal", "tourism": "artwork"}}, {"type": "node", "id": 9802285247, "lat": 47.2869963, "lon": 18.6601732, "tags": {"artist_name": "M\u00e1hr Ferenc", "artwork_type": "statue", "material": "stone", "name": "Szent Vendel", "start_date": "2017", "tourism": "artwork"}}, {"type": "node", "id": 9807094370, "lat": 46.9648555, "lon": 18.9403882, "tags": {"artwork_type": "sculpture", "name": "Duna\u00fajv\u00e1ros", "tourism": "artwork"}}, {"type": "node", "id": 9864080541, "lat": 47.2831676, "lon": 18.6545612, "tags": {"artwork_type": "statue", "name": "Faragott fa szobrok", "tourism": "artwork"}}, {"type": "node", "id": 10308197809, "lat": 46.9616274, "lon": 18.9506686, "tags": {"artwork_type": "sculpture", "material": "steel", "source": "http://steelsculpture.art/hu/szoborpark/", "start_date": "1975", "tourism": "artwork"}}, {"type": "node", "id": 10593797225, "lat": 47.2764548, "lon": 19.066169, "tags": {"artwork_type": "sculpture", "name": "#Dunavars\u00e1ny", "tourism": "artwork"}}, {"type": "node", "id": 10593797232, "lat": 47.2764102, "lon": 19.0657666, "tags": {"artwork_type": "statue", "name": "Gr\u00f3f Tisza Istv\u00e1n", "tourism": "artwork"}}, {"type": "node", "id": 10593797234, "lat": 47.2763347, "lon": 19.06589, "tags": {"artwork_type": "statue", "name": "Gr\u00f3f Batthy\u00e1ny Lajos", "tourism": "artwork"}}, {"type": "way", "id": 1002233525, "nodes": [9249965381, 9249965382, 9249965383, 9249965384, 9249965381], "tags": {"area": "yes", "artist_name": "Billy Lee", "artwork_type": "sculpture", "material": "steel", "name": "M\u00e1ty\u00e1s kir\u00e1ly eml\u00e9k\u00e9re", "source": "http://steelsculpture.art/hu/szoborpark/", "start_date": "1996", "tourism": "artwork"}}, {"type": "way", "id": 1002233526, "nodes": [9249965385, 9249965386, 9249965387, 9249965388, 9249965385], "tags": {"area": "yes", "artist_name": "Buczk\u00f3 Gy\u00f6rgy", "artwork_type": "sculpture", "material": "steel", "name": "T\u00e9rplasztika", "start_date": "1979", "tourism": "artwork"}}, {"type": "way", "id": 1002233527, "nodes": [9249965389, 9249965390, 9249965391, 9249965392, 9249965389], "tags": {"area": "yes", "artist_name": "Wang Sheng Jin", "artwork_type": "sculpture", "material": "steel", "name": "Kelet \u00e9s Nyugat", "source": "http://steelsculpture.art/hu/szoborpark/", "start_date": "1996", "tourism": "artwork"}}, {"type": "way", "id": 1002233528, "nodes": [9249965393, 9249965394, 9249965395, 9249965396, 9249965393], "tags": {"area": "yes", "artist_name": "Ga\u00e1l Tam\u00e1s", "artwork_type": "sculpture", "material": "steel", "name": "Part-P\u00e1r", "source": "http://steelsculpture.art/hu/szoborpark/", "start_date": "2000", "tourism": "artwork"}}, {"type": "way", "id": 1055475546, "nodes": [9698465545, 9698465546, 9698465547, 9698465548, 9698465549, 9698465550, 9698465551, 9698465552, 9698465553, 9698465554, 9698465555, 9698465556, 9698465557, 9698465558, 9698465559, 9698465560, 9698465561], "tags": {"artist_name": "Fridrich Ferenc", "artwork_type": "statue", "tourism": "artwork"}}]}