{"version": 0.6, "generator": "Overpass API 0.7.59 e21c39fe", "osm3s": {"timestamp_osm_base": "2023-03-01T09:35:38Z", "copyright": "The data included in this document is from www.openstreetmap.org. The data is made available under ODbL."}, "elements": [{"type": "node", "id": 3329072416, "lat": 47.336468, "lon": 21.090789, "tags": {"access": "private", "man_made": "tower", "name": "Kil\u00e1t\u00f3", "source": "turistautak.hu", "tourism": "viewpoint", "tower:type": "observation", "url": "http://turistautak.hu/poi.php?id=22559"}}, {"type": "node", "id": 3432034692, "lat": 47.274353, "lon": 21.421131, "tags": {"man_made": "tower", "name": "Mad\u00e1rfigyel\u0151 torony", "source": "turistautak.hu", "tourism": "viewpoint", "tower:type": "observation", "url": "http://turistautak.hu/poi.php?id=72058"}}]}