{"version": 0.6, "generator": "Overpass API 0.7.59 e21c39fe", "osm3s": {"timestamp_osm_base": "2023-03-01T08:44:58Z", "copyright": "The data included in this document is from www.openstreetmap.org. The data is made available under ODbL."}, "elements": [{"type": "node", "id": 541385477, "lat": 48.1042479, "lon": 21.6530755, "tags": {"artwork_type": "statue", "name": "Kossuth-szobor", "tourism": "artwork"}}, {"type": "node", "id": 3066781001, "lat": 47.9532578, "lon": 21.7151341, "tags": {"artwork_type": "statue", "name": "Magyar husz\u00e1r", "tourism": "artwork"}}, {"type": "node", "id": 3068679424, "lat": 47.9564057, "lon": 21.7162794, "tags": {"artwork_type": "statue", "name": "V\u00e1rosalap\u00edt\u00f3 aty\u00e1k", "tourism": "artwork"}}, {"type": "node", "id": 3198353986, "lat": 47.9560956, "lon": 21.7169929, "tags": {"artwork_type": "makett", "name": "Belv\u00e1ros makettje", "tourism": "artwork"}}, {"type": "node", "id": 3227790723, "lat": 47.9543333, "lon": 21.7121489, "tags": {"artwork_type": "statue", "name": "Th\u00e1lia", "tourism": "artwork"}}, {"type": "node", "id": 3227796817, "lat": 48.0051194, "lon": 21.7254286, "tags": {"artist_name": "Csontos L\u00e1szl\u00f3", "artwork_type": "statue", "mapillary": "875129503041266", "name": "Fekv\u0151 n\u0151", "start_date": "1966", "tourism": "artwork"}}, {"type": "node", "id": 3227797861, "lat": 48.0050439, "lon": 21.7246646, "tags": {"artist_name": "Halm\u00e1gyi Istv\u00e1n", "artwork_type": "statue", "name": "Kors\u00f3viv\u0151", "start_date": "1940", "tourism": "artwork"}}, {"type": "node", "id": 3274467832, "lat": 47.9528673, "lon": 21.7153831, "tags": {"artwork_type": "plate", "name": "Szarvas pal\u00e9ta", "tourism": "artwork"}}, {"type": "node", "id": 3274473187, "lat": 47.9583639, "lon": 21.7140822, "tags": {"artwork_type": "obelisk", "name": "\u00c9letfa", "tourism": "artwork"}}, {"type": "node", "id": 3274560164, "lat": 47.9580151, "lon": 21.7162941, "tags": {"artwork_type": "relief", "name": "Szabolcsi alma", "tourism": "artwork"}}, {"type": "node", "id": 3412799857, "lat": 47.9606865, "lon": 21.7055956, "tags": {"artwork_type": "statue", "tourism": "artwork"}}, {"type": "node", "id": 3417746250, "lat": 47.9545829, "lon": 21.7142618, "tags": {"artwork_type": "statue", "name": "V\u00edzhord\u00f3 kisl\u00e1ny", "tourism": "artwork"}}, {"type": "node", "id": 3459024325, "lat": 48.0041156, "lon": 21.7252128, "tags": {"artist_name": "Nagy S\u00e1ndor", "artwork_type": "obelisk", "name": "\u00c1ll\u00f3 n\u0151", "start_date": "1966", "tourism": "artwork"}}, {"type": "node", "id": 3471735418, "lat": 47.877926, "lon": 22.022882, "tags": {"artwork_type": "statue", "source": "turistautak.hu", "source:date": "2011-09-23", "tourism": "artwork", "url": "http://turistautak.hu/poi.php?id=95155"}}, {"type": "node", "id": 3471735421, "lat": 47.878671, "lon": 22.023939, "tags": {"artwork_type": "statue", "source": "turistautak.hu", "source:date": "2011-09-23", "tourism": "artwork", "url": "http://turistautak.hu/poi.php?id=95158"}}, {"type": "node", "id": 3484823506, "lat": 48.00015, "lon": 22.16525, "tags": {"artwork_type": "statue", "name": "Angyal szobor", "source": "turistautak.hu", "source:date": "2013-05-18", "tourism": "artwork", "url": "http://turistautak.hu/poi.php?id=153623"}}, {"type": "node", "id": 3488372771, "lat": 47.956994, "lon": 21.715316, "tags": {"name": "Szerelmesek lakatjai", "source": "turistautak.hu", "source:date": "2010-01-26", "tourism": "artwork", "url": "http://turistautak.hu/poi.php?id=84034"}}, {"type": "node", "id": 3500505728, "lat": 47.9554422, "lon": 21.7178439, "tags": {"artwork_type": "makett", "name": "Templommakett", "tourism": "artwork"}}, {"type": "node", "id": 3500524513, "lat": 47.9702463, "lon": 21.7143503, "tags": {"artwork_type": "statue", "name": "Diszkoszvet\u0151", "tourism": "artwork"}}, {"type": "node", "id": 3500524514, "lat": 48.0055606, "lon": 21.7277913, "tags": {"artist_name": "Kincses M\u00e1ria", "artwork_type": "statue", "name": "Napoz\u00f3", "start_date": "1979", "tourism": "artwork"}}, {"type": "node", "id": 3500526462, "lat": 48.0016993, "lon": 21.7235, "tags": {"artist_name": "Orr Lajos", "artwork_type": "statue", "name": "Zsir\u00e1fcsal\u00e1d", "start_date": "2001", "tourism": "artwork"}}, {"type": "node", "id": 3525643419, "lat": 47.9542343, "lon": 21.7121134, "tags": {"artwork_type": "statue", "tourism": "artwork"}}, {"type": "node", "id": 4226255053, "lat": 47.9726155, "lon": 21.7159519, "tags": {"artwork_type": "statue", "tourism": "artwork"}}, {"type": "node", "id": 4535065565, "lat": 48.1353655, "lon": 22.1137692, "tags": {"name": "MIG-21 Vad\u00e1szrep\u00fcl\u0151 eml\u00e9km\u0171", "tourism": "artwork"}}, {"type": "node", "id": 4852388673, "lat": 48.1207354, "lon": 21.70889, "tags": {"artwork_type": "sculpture", "tourism": "artwork"}}, {"type": "node", "id": 4852464296, "lat": 48.1216159, "lon": 21.7030234, "tags": {"artwork_type": "sculpture", "name": "Millenniumi eml\u00e9km\u0171 (Turul-szobor)", "tourism": "artwork"}}, {"type": "node", "id": 5577113525, "lat": 48.1339432, "lon": 21.7518674, "tags": {"artist_name": "Kotricz T\u00fcnde", "artwork_type": "statue", "name": "Nagy hal\u00e1sz", "tourism": "artwork"}}, {"type": "node", "id": 5912346321, "lat": 48.1353585, "lon": 22.1136459, "tags": {"artwork_type": "statue", "name": "Gagarin szobor", "tourism": "artwork"}}, {"type": "node", "id": 9724523451, "lat": 47.8375099, "lon": 22.1330676, "tags": {"alt_name": "A k\u00f6z\u00e9pkori s\u00f3\u00fat eml\u00e9kszobra", "artist:wikidata": "Q56525284", "artist_name": "Mihajlo Kolodko", "artist_name:hu": "Kolodko Mih\u00e1ly", "artwork_subject": "figurative", "artwork_type": "statue", "contact:email": "info@kolodkoart.com", "contact:facebook": "https://www.facebook.com/misha.kolodko", "contact:instagram": "kolodkomini", "contact:website": "http://kolodkoart.com/", "location": "wall", "material": "stone;bronze", "name": "S\u00f3keresked\u0151", "start_date": "2021", "tourism": "artwork", "url": "https://www.kozterkep.hu/45399/sokereskedo"}}, {"type": "node", "id": 9724523452, "lat": 47.8758186, "lon": 21.8469719, "tags": {"artist:wikidata": "Q56525284", "artist_name": "Mihajlo Kolodko", "artist_name:hu": "Kolodko Mih\u00e1ly", "artwork_subject": "figurative", "artwork_type": "statue", "contact:email": "info@kolodkoart.com", "contact:facebook": "https://www.facebook.com/misha.kolodko", "contact:instagram": "kolodkomini", "contact:website": "http://kolodkoart.com/", "location": "wall", "material": "stone;bronze", "name": "S\u00f3keresked\u0151", "start_date": "2021", "tourism": "artwork", "url": "https://www.kozterkep.hu/43580/sokereskedo"}}, {"type": "node", "id": 10043727366, "lat": 47.8097457, "lon": 21.8518577, "tags": {"artist_name": "Mihajlo Kolodko;S\u00e1rga Gy\u00f6rgy", "artist_name:hu": "Kolodko Mih\u00e1ly;S\u00e1rga Gy\u00f6rgy k\u0151szobr\u00e1sz \u00e9s k\u0151farag\u00f3 mester", "artwork_type": "statue", "description": "A szoborcsoport els\u0151dleges c\u00e9lja a falu megalap\u00edt\u00f3ja, gr\u00f3f nagyk\u00e1ll\u00f3i K\u00e1llay (XIII.) J\u00e1nos P\u00e9ter (1735-1810) eml\u00e9k\u00e9nek\nmeg\u0151rz\u00e9se. Tizenk\u00e9t faragott k\u00f6nyvb\u0151l \u00e1ll, melyek k\u00f6z\u00fcl tizenegy fekszik, egy pedig \u00e1ll, melyen a gr\u00f3f \u00fcl\u0151 miniat\u0171r szobra van.", "name": "Gr\u00f3f K\u00f6nyvt\u00e1ra szoborcsoport", "source": "http://www.biri.hu/files/birihirmondo/BH2021-21-2.pdf", "start_date": "2021-03-27", "tourism": "artwork"}}, {"type": "node", "id": 10144758907, "lat": 47.969811, "lon": 22.2453629, "tags": {"artwork_type": "statue", "tourism": "artwork"}}]}